{
  "version": 1,
  "serviceConfiguration": {
    "apiName": "vitapp",
    "serviceName": "AppSync",
    "gqlSchemaPath": "/tmp/amplify-4320e109-c5be-46ba-88c4-bf2e39f57be9/amplify/backend/api/vitapp/schema.graphql",
    "defaultAuthType": {
      "mode": "API_KEY",
      "keyDescription": "api key description",
      "expirationTime": 30
    },
    "additionalAuthTypes": [
      {
        "mode": "AWS_IAM"
      }
    ],
    "conflictResolution": {
      "defaultResolutionStrategy": {
        "type": "AUTOMERGE"
      }
    }
  }
}